dynamicsettings/__init__.py
dynamicsettings/admin.py
dynamicsettings/apps.py
dynamicsettings/models.py
dynamicsettings/migrations/0001_initial.py
dynamicsettings/migrations/__init__.py
django_dynamicsettings-0.0.3.dist-info/LICENSE
django_dynamicsettings-0.0.3.dist-info/METADATA
django_dynamicsettings-0.0.3.dist-info/WHEEL
django_dynamicsettings-0.0.3.dist-info/top_level.txt
django_dynamicsettings-0.0.3.dist-info/RECORD
