Metadata-Version: 2.1
Name: django-dynamicsettings
Version: 0.0.3
Summary: use dynamic (database) settings in your settings.py
Home-page: https://github.com/fopina/django-dynamicsettings/
Author: Filipe Pina
Author-email: fopina@gmail.com
License: BSD
Download-URL: https://pypi.org/project/django-dynamicsettings/
Platform: UNKNOWN
Classifier: Development Status :: 5 - Production/Stable
Classifier: Environment :: Web Environment
Classifier: Framework :: Django
Classifier: Framework :: Django :: 2.2
Classifier: Framework :: Django :: 3.0
Classifier: Intended Audience :: Developers
Classifier: License :: OSI Approved :: BSD License
Classifier: Operating System :: OS Independent
Classifier: Programming Language :: Python
Classifier: Programming Language :: Python :: 3
Classifier: Programming Language :: Python :: 3 :: Only
Classifier: Programming Language :: Python :: 3.6
Classifier: Programming Language :: Python :: 3.7
Classifier: Programming Language :: Python :: 3.8
Classifier: Topic :: Software Development :: Libraries :: Python Modules
Requires-Python: >=3.6
Requires-Dist: Django (>=2.2)
